{
  "timestamp": "2026-07-23T18:29:53.005Z",
  "openspecVersion": "unknown",
  "openloreVersion": "1.0.0",
  "filesWritten": [
    "openspec/specs/overview/spec.md",
    "openspec/specs/provider/spec.md",
    "openspec/specs/model/spec.md",
    "openspec/specs/auth/spec.md",
    "openspec/specs/connection/spec.md",
    "openspec/specs/combo/spec.md",
    "openspec/specs/quota/spec.md",
    "openspec/specs/cache/spec.md",
    "openspec/specs/compression/spec.md",
    "openspec/specs/proxy/spec.md",
    "openspec/specs/usage/spec.md",
    "openspec/specs/backup/spec.md",
    "openspec/specs/log/spec.md",
    "openspec/specs/architecture/spec.md",
    "openspec/specs/api/spec.md"
  ],
  "filesSkipped": [],
  "filesBackedUp": [],
  "filesMerged": [],
  "domainsRemoved": [],
  "configUpdated": true,
  "validationErrors": [],
  "warnings": [],
  "nextSteps": [
    "Review generated specs: openspec list --specs",
    "Validate structure: openspec validate --all",
    "Test accuracy: openlore verify",
    "Create a change proposal: openspec change my-feature"
  ]
}